alu/ALU.v
module ALU(
    input [7:0] a,
    input [7:0] b,
    input [3:0] opCode,
    output reg [7:0] result,
    output reg zero,
    output reg carry,
    output reg overflow
);
    reg [8:0] temp_sum;

    always @(*) begin
        case(opCode)
            4'b0000: begin // ADD
                temp_sum = a + b; 
                result   = temp_sum[7:0];
                
                // Status
                carry    = temp_sum[8];
                zero     = (temp_sum[7:0] == 8'b0);
                overflow = (~a[7] & ~b[7] & result[7]) | (a[7] & b[7] & ~result[7]);
            end
            4'b0001: begin // SUB
                result   = a - b;
                
                // Status
                carry    = (a >= b);
                zero     = (result == 8'b0);
                overflow = (a[7] != b[7]) && (result[7] != a[7]);
            end
            4'b0011: begin // INC
                result = a + 8'b0000_0001;

                // Status
                carry    = 8'b0;
                zero     = 8'b0;
                overflow = 8'b0;
            end
            4'b0010: begin // DEC
                result = a - 8'b0000_0001;

                // Status
                carry    = 8'b0;
                zero     = 8'b0;
                overflow = 8'b0;
            end
            4'b0110: begin // NEG
                result = ~a + 1;

                // Status
                carry    = 8'b0;
                zero     = 8'b0;
                overflow = 8'b0;
            end
            4'b0111: begin // NOT
                result   = ~a;
                
                // Status
                carry    = 8'b0;
                zero     = 8'b0;
                overflow = 8'b0;
            end
            4'b0101: begin // AND
                result = a & b;

                // Status
                carry    = 8'b0;
                zero     = 8'b0;
                overflow = 8'b0;
            end
            4'b1000: begin // OR
                result = a | b;
                
                // Status
                carry    = 8'b0;
                zero     = 8'b0;
                overflow = 8'b0;
            end
            4'b1100: begin // XOR
                result = a ^ b;

                // Status
                carry    = 8'b0;
                zero     = 8'b0;
                overflow = 8'b0;
            end
            default: begin 
                result = 8'b0;
                
                // Status
                carry = 1'b0;
                zero = 1'b1;
                overflow = 1'b0;
            end
        endcase
    end    
endmodule

// GT
    // LT
    // 1's COMP
    // 2'S COMP

    // case(opCode):
    //     4'b000: result = a & b; // AND 
    //     4'b001: result = a | b; // OR
    //     4'b010: result = a ^ b; // XOR
    //     4'b011: result = a + b; // ADD
    //     4'b100: result = a - b; // SUB
    //     4'b101: result = (a < b) ? 8'b1 : 8'b0 // SLT
    //     4'b101: result = (a == b) ? 8'b1 : 8'b0 // EQ
    // endcase

alu/ALU_tb.v
`timescale 1ps/1ps

module ALU_tb;
    reg [7:0] a, b;
    reg [2:0] opCode;
    wire [7:0] result;
    wire zero;
    wire carry;
    wire overflow;

    ALU uut (
        .a(a),
        .b(b),
        .opCode(opCode),
        .result(result),
        .zero(zero),
        .carry(carry),
        .overflow(overflow)
    );

    initial begin
        $dumpfile("wave.vcd");
        $dumpvars(0, ALU_tb);

        // *********************ADD Operation Tests*********************
        opCode = 3'b000;

        // Nominal addition: Basic operation, in-range
        a = 8'd1;
        b = 8'd2;
        #10;

        // Addition -> zero: Edge case for zero
        a = 8'd0;
        b = 8'd0;
        #10;

        // Max unsigned (255 + 0): Edge of range, no wrap
        a = 8'd255;
        b = 8'd0;
        #10;

        // Unsigned overflow: Carry-out without signed overflow
        a = 8'd255;
        b = 8'd1;
        #10;

        // Signed overflow (+127 + 1): 01111111 + 00000001 = 10000000
        a = 8'd127;
        b = 8'd1;
        #10;

        // Signed overflow (-64 + -64): 11000000 + 11000000 = 10000000
        a = 8'd192;
        b = 8'd192;
        #10;

        // Postive + Negative: Mixed sign, no overflow
        a = 8'd50;
        b = 8'd206;
        #10;
                
        // Negative + Positive: Mixed sign, no overflow
        a = 8'd200;
        b = 8'd60;
        #10;        
        
        //*********************SUB Operation Tests*********************
        opCode = 3'b001;

        // Nominal subtraction: Basic operation, in-range
        a = 8'd10;
        b = 8'd3;    
        #10;
    
        // Subtraction -> zero: a - a = 0
        a = 8'd77;
        b = 8'd77;
        #10;

        // Unsigned borrow: a < b → wrap
        a = 8'd5;
        b = 8'd10;
        #10;

        // Signed underflow: -128 - 1 → overflow
        a = 8'd128; // -128
        b = 8'd1;
        #10;

        // Signed overflow: 127 - (-1) → wraps negative
        a = 8'd127;
        b = 8'd255; // -1 in two's comp
        #10;

        // Positive - Negative: large positive result, no overflow
        a = 8'd100;
        b = 8'd200; // -56 in signed
        #10;

        // Negative - Positive: large negative result
        a = 8'd200; // -56 in signed
        b = 8'd100;
        #10;
        
        // Subtract - edge: 0 - 255 = 1 (since -(-1) = 1)
        a = 8'd0;
        b = 8'd255;
        #10;
             
        $finish;
    end

endmodule

alu/wave.vcd
$date
	Sun Jul 27 20:21:21 2025
$end
$version
	Icarus Verilog
$end
$timescale
	1ps
$end
$scope module ALU_tb $end
$var wire 1 ! zero $end
$var wire 8 " result [7:0] $end
$var wire 1 # overflow $end
$var wire 1 $ carry $end
$var reg 8 % a [7:0] $end
$var reg 8 & b [7:0] $end
$var reg 3 ' opCode [2:0] $end
$scope module uut $end
$var wire 8 ( a [7:0] $end
$var wire 8 ) b [7:0] $end
$var wire 4 * opCode [3:0] $end
$var reg 1 $ carry $end
$var reg 1 # overflow $end
$var reg 8 + result [7:0] $end
$var reg 9 , temp_sum [8:0] $end
$var reg 1 ! zero $end
$upscope $end
$upscope $end
$enddefinitions $end
$comment Show the parameter values. $end
$dumpall
$end
#0
$dumpvars
b11 ,
b11 +
b0 *
b10 )
b1 (
b0 '
b10 &
b1 %
0$
0#
b11 "
0!
$end
#10
1!
b0 "
b0 +
b0 ,
b0 &
b0 )
b0 %
b0 (
#20
0!
b11111111 "
b11111111 +
b11111111 ,
b11111111 %
b11111111 (
#30
1!
1$
b0 "
b0 +
b100000000 ,
b1 &
b1 )
#40
1#
0!
0$
b10000000 "
b10000000 +
b10000000 ,
b1111111 %
b1111111 (
#50
0#
1$
b110000000 ,
b11000000 &
b11000000 )
b11000000 %
b11000000 (
#60
1!
b0 "
b0 +
b100000000 ,
b11001110 &
b11001110 )
b110010 %
b110010 (
#70
0!
b100 "
b100 +
b100000100 ,
b111100 &
b111100 )
b11001000 %
b11001000 (
#80
b111 "
b111 +
b11 &
b11 )
b1010 %
b1010 (
b1 *
b1 '
#90
1!
b0 "
b0 +
b1001101 &
b1001101 )
b1001101 %
b1001101 (
#100
0!
0$
b11111011 "
b11111011 +
b1010 &
b1010 )
b101 %
b101 (
#110
1#
1$
b1111111 "
b1111111 +
b1 &
b1 )
b10000000 %
b10000000 (
#120
0$
b10000000 "
b10000000 +
b11111111 &
b11111111 )
b1111111 %
b1111111 (
#130
b10011100 "
b10011100 +
b11001000 &
b11001000 )
b1100100 %
b1100100 (
#140
1$
b1100100 "
b1100100 +
b1100100 &
b1100100 )
b11001000 %
b11001000 (
#150
0#
0$
b1 "
b1 +
b11111111 &
b11111111 )
b0 %
b0 (
