control_unit/control_unit.v
module control_unit(
    input [3:0] opCode,
    output reg n_reg_w,
    output reg n_mem_rw,
    output reg n_mem_cs,
    output reg n_mem_oe
);
    localparam OP_LD   = 4'b0000;
    localparam OP_LDI  = 4'b0001;
    localparam OP_ST   = 4'b0011;
    localparam OP_ADD  = 4'b0010;
    localparam OP_SUB  = 4'b0110;
    localparam OP_AND  = 4'b0111;
    localparam OP_OR   = 4'b0101;
    localparam OP_XOR  = 4'b0100;
    localparam OP_NOT  = 4'b1100;
    localparam OP_SLL  = 4'b1101;
    localparam OP_SRL  = 4'b1111;
    localparam OP_SRA  = 4'b1110;
    localparam OP_BEQ  = 4'b1010;
    localparam OP_BNE  = 4'b1011;
    localparam OP_JMP  = 4'b1001;
    localparam OP_JAL  = 4'b1000;

    always @(*) begin
        n_reg_w  = 1'b1;
        n_mem_rw = 1'b1;
        n_mem_cs = 1'b1;
        n_mem_oe = 1'b1;

        case(opCode)
            OP_LD: begin // LD
                n_mem_cs = 1'b0;
                n_mem_oe = 1'b0;
                n_mem_rw = 1'b0;
                n_reg_w  = 1'b0;
            end
            OP_LDI: begin // LDI
                n_reg_w = 1'b0;
            end
            OP_ST: begin // ST
                n_mem_cs = 1'b0;
                n_mem_rw = 1'b1;
            end
            OP_ADD, OP_SUB, OP_AND, OP_OR, OP_XOR, 
            OP_NOT, OP_SLL, OP_SRL, OP_SRA: begin
                n_reg_w = 1'b0;
            end
            OP_BEQ, OP_BNE, OP_JMP: begin // BEQ, BNE, JMP
                // Only update PC, no reg writes
            end
            OP_JAL: begin // JAL
                n_reg_w = 1'b0;
            end
            default: ;
        endcase
    end
endmodule

control_unit/control_unit_tb.v
`timescale 1ns/1ns

module control_unit_tb;
    reg [3:0] opCode;
    wire n_reg_w;
    wire n_mem_rw;
    wire n_mem_cs;
    wire n_mem_oe;

    // Instantiate the control_unit
    control_unit uut (
        .opCode(opCode),
        .n_reg_w(n_reg_w),
        .n_mem_rw(n_mem_rw),
        .n_mem_cs(n_mem_cs),
        .n_mem_oe(n_mem_oe)
    );

    // Array of opcodes in Gray code order
    reg [3:0] op_codes [0:15];
    integer i;

    initial begin
        // Set up waveform dump
        $dumpfile("control_unit.vcd");
        $dumpvars(0, control_unit_tb);

        // Initialize Gray code sequence and names
        op_codes[0]  = 4'b0000;
        op_codes[1]  = 4'b0001;
        op_codes[2]  = 4'b0011;
        op_codes[3]  = 4'b0010;
        op_codes[4]  = 4'b0110;
        op_codes[5]  = 4'b0111;
        op_codes[6]  = 4'b0101;
        op_codes[7]  = 4'b0100;
        op_codes[8]  = 4'b1100;
        op_codes[9]  = 4'b1101;
        op_codes[10] = 4'b1111;
        op_codes[11] = 4'b1110;
        op_codes[12] = 4'b1010;
        op_codes[13] = 4'b1011;
        op_codes[14] = 4'b1001;
        op_codes[15] = 4'b1000;

        // Cycle through the op_codes
        for (i = 0; i < 16; i = i + 1) begin
            opCode = op_codes[i];
            #10;
        end

        #10 $finish;
    end
endmodule

control_unit/control_unit.vcd
$date
	Sun Jul 27 21:20:09 2025
$end
$version
	Icarus Verilog
$end
$timescale
	1ns
$end
$scope module control_unit_tb $end
$var wire 1 ! n_reg_w $end
$var wire 1 " n_mem_rw $end
$var wire 1 # n_mem_oe $end
$var wire 1 $ n_mem_cs $end
$var reg 4 % opCode [3:0] $end
$var integer 32 & i [31:0] $end
$scope module uut $end
$var wire 4 ' opCode [3:0] $end
$var parameter 4 ( OP_ADD $end
$var parameter 4 ) OP_AND $end
$var parameter 4 * OP_BEQ $end
$var parameter 4 + OP_BNE $end
$var parameter 4 , OP_JAL $end
$var parameter 4 - OP_JMP $end
$var parameter 4 . OP_LD $end
$var parameter 4 / OP_LDI $end
$var parameter 4 0 OP_NOT $end
$var parameter 4 1 OP_OR $end
$var parameter 4 2 OP_SLL $end
$var parameter 4 3 OP_SRA $end
$var parameter 4 4 OP_SRL $end
$var parameter 4 5 OP_ST $end
$var parameter 4 6 OP_SUB $end
$var parameter 4 7 OP_XOR $end
$var reg 1 $ n_mem_cs $end
$var reg 1 # n_mem_oe $end
$var reg 1 " n_mem_rw $end
$var reg 1 ! n_reg_w $end
$upscope $end
$upscope $end
$enddefinitions $end
$comment Show the parameter values. $end
$dumpall
b100 7
b110 6
b11 5
b1111 4
b1110 3
b1101 2
b101 1
b1100 0
b1 /
b0 .
b1001 -
b1000 ,
b1011 +
b1010 *
b111 )
b10 (
$end
#0
$dumpvars
b0 '
b0 &
b0 %
0$
0#
0"
0!
$end
#10
1#
1$
1"
0!
b1 %
b1 '
b1 &
#20
0$
1!
b11 %
b11 '
b10 &
#30
0!
1$
b10 %
b10 '
b11 &
#40
0!
b110 %
b110 '
b100 &
#50
0!
b111 %
b111 '
b101 &
#60
0!
b101 %
b101 '
b110 &
#70
0!
b100 %
b100 '
b111 &
#80
0!
b1100 %
b1100 '
b1000 &
#90
0!
b1101 %
b1101 '
b1001 &
#100
0!
b1111 %
b1111 '
b1010 &
#110
0!
b1110 %
b1110 '
b1011 &
#120
1!
b1010 %
b1010 '
b1100 &
#130
b1011 %
b1011 '
b1101 &
#140
b1001 %
b1001 '
b1110 &
#150
0!
b1000 %
b1000 '
b1111 &
#160
b10000 &
